{
	"format_version": "1.8.0",
	"animations": {
		"grab_ready": {
			"loop": "hold_on_last_frame",
			"animation_length": 0.25,
			"bones": {
				"right_arm": {
					"rotation": {
						"0.0": {
							"post": [0, 0, 0],
							"lerp_mode": "catmullrom"
						},
						"0.2083": {
							"post": [-75.81268, 17.53754, -10.54301],
							"lerp_mode": "catmullrom"
						}
					}
				},
				"left_arm": {
					"rotation": {
						"0.0": {
							"post": [0, 0, 0],
							"lerp_mode": "catmullrom"
						},
						"0.2083": {
							"post": [-82.884, -17.46205, 22.79343],
							"lerp_mode": "catmullrom"
						}
					}
				}
			}
		}
	}
}