{
	"format_version": "1.8.0",
	"animations": {
		"push_fp": {
			"animation_length": 0.8,
			"loop": false,
			"bones": {
				"rightArm": {
					"rotation": {
						"0.0": [-45, 15, 0],
						"0.3": [-120, 15, 0],
						"0.6": [-90, 10, 0],
						"0.8": [0, 0, 0]
					},
					"position": {
						"0.0": [-1, 1, 2],
						"0.3": [-1, 4, 3],
						"0.6": [-0.5, 3, 3],
						"0.8": [0, 2, 3]
					}
				},
				"leftArm": {
					"rotation": {
						"0.0": [-45, -15, 0],
						"0.3": [-120, -15, 0],
						"0.6": [-90, -10, 0],
						"0.8": [0, 0, 0]
					},
					"position": {
						"0.0": [1, 1, 2],
						"0.3": [1, 4, 3],
						"0.6": [0.5, 3, 3],
						"0.8": [0, 2, 3]
					}
				}
			}
		}
	}
}
